LICENSE
MANIFEST.in
README.rst
beefish.py
setup.py
beefish.egg-info/PKG-INFO
beefish.egg-info/SOURCES.txt
beefish.egg-info/dependency_links.txt
beefish.egg-info/requires.txt
beefish.egg-info/top_level.txt