Metadata-Version: 1.1
Name: beefish
Version: 0.2.0
Summary: simple file encryption using pycrypto
Home-page: http://github.com/coleifer/beefish/
Author: Charles Leifer
Author-email: coleifer@gmail.com
License: UNKNOWN
Platform: UNKNOWN
Classifier: Development Status :: 5 - Production/Stable
Classifier: Intended Audience :: Developers
Classifier: License :: OSI Approved :: MIT License
Classifier: Operating System :: OS Independent
Classifier: Programming Language :: Python
